coramin/__init__.py
coramin/algorithms/__init__.py
coramin/algorithms/ecp_bounder.py
coramin/algorithms/multitree/__init__.py
coramin/algorithms/multitree/multitree.py
coramin/algorithms/multitree/tests/__init__.py
coramin/algorithms/multitree/tests/test_multitree.py
coramin/domain_reduction/__init__.py
coramin/domain_reduction/dbt.py
coramin/domain_reduction/filters.py
coramin/domain_reduction/obbt.py
coramin/relaxations/__init__.py
coramin/relaxations/_utils.py
coramin/relaxations/alphabb.py
coramin/relaxations/auto_relax.py
coramin/relaxations/copy_relaxation.py
coramin/relaxations/custom_block.py
coramin/relaxations/hessian.py
coramin/relaxations/iterators.py
coramin/relaxations/mccormick.py
coramin/relaxations/multivariate.py
coramin/relaxations/relaxations_base.py
coramin/relaxations/segments.py
coramin/relaxations/split_expr.py
coramin/relaxations/univariate.py
coramin/third_party/__init__.py
coramin/third_party/minlplib_tools.py
coramin/utils/__init__.py
coramin/utils/coramin_enums.py
coramin/utils/mpi_utils.py
coramin/utils/plot_relaxation.py
coramin/utils/pyomo_utils.py
coramin-0.2.4.dist-info/LICENSE.txt
coramin-0.2.4.dist-info/METADATA
coramin-0.2.4.dist-info/WHEEL
coramin-0.2.4.dist-info/top_level.txt
coramin-0.2.4.dist-info/RECORD
