Metadata-Version: 2.1
Name: coramin
Version: 0.2.4
Summary: Coramin: Pyomo tools for MINLP
Home-page: https://github.com/Coramin/Coramin
Author: Coramin Developers
Maintainer-email: mlbynum@sandia.gov
License: Revised BSD
Classifier: Programming Language :: Python :: 3
Classifier: Programming Language :: Python :: 3.7
Classifier: Programming Language :: Python :: 3.8
Classifier: Programming Language :: Python :: 3.9
Classifier: License :: OSI Approved :: BSD License
Classifier: Operating System :: OS Independent
Requires-Python: >=3.7
License-File: LICENSE.txt
Requires-Dist: pyomo (>=6.4.1)
Requires-Dist: numpy
Requires-Dist: scipy
Requires-Dist: networkx
